setup.cfg
setup.py
cronus/__init__.py
cronus/beat.py
cronus/test_beat.py
cronus/test_timeout.py
cronus/timeout.py
cronus.egg-info/PKG-INFO
cronus.egg-info/SOURCES.txt
cronus.egg-info/dependency_links.txt
cronus.egg-info/not-zip-safe
cronus.egg-info/top_level.txt