Metadata-Version: 1.0
Name: cronus
Version: 0.2
Summary: The Greek God of Time
Home-page: http://github.com/anayjoshi/cronus
Author: Anaykumar Joshi
Author-email: anaykumar.joshi@gmail.com
License: BSD
Platform: UNKNOWN
